pjdev_sqlmodel/__about__.py
pjdev_sqlmodel/__init__.py
pjdev_sqlmodel/settings_service.py
pjdev_sqlmodel/sqlmodel_service.py
pjdev_sqlmodel/utilities.py
pjdev_sqlmodel/models/__init__.py
pjdev_sqlmodel/models/db_models.py
pjdev_sqlmodel/models/settings_models.py
pjdev_sqlmodel-4.6.3.dist-info/METADATA
pjdev_sqlmodel-4.6.3.dist-info/WHEEL
pjdev_sqlmodel-4.6.3.dist-info/licenses/LICENSE.txt
pjdev_sqlmodel-4.6.3.dist-info/RECORD
